[{"start":"03:00","startTime":"20260419030000","stopTime":"20260419044100","program":"音乐会/Christian Thielemann指挥钢琴家I.Levit和维也纳爱乐:布拉姆斯第1号钢琴协奏曲与第2号交响曲(普)"},{"start":"04:41","startTime":"20260419044100","stopTime":"20260419060000","program":"音乐会/Christian Thielemann指挥钢琴家I.Levit和维也纳爱乐:布拉姆斯第2号钢琴协奏曲与第3号交响曲(普)"},{"start":"06:00","startTime":"20260419060000","stopTime":"20260419074800","program":"音乐会/弗罗茨瓦夫音乐节:Christoph Eschenbach指挥NFM弗罗茨瓦夫爱乐演奏布鲁克纳作品(普)"},{"start":"07:48","startTime":"20260419074800","stopTime":"20260419080000","program":"InterMezzo 爱乐间奏(普)"},{"start":"08:00","startTime":"20260419080000","stopTime":"20260419102100","program":"歌剧/维也纳国立歌剧院:普契尼《杜兰朵》(普)"},{"start":"10:21","startTime":"20260419102100","stopTime":"20260419120000","program":"音乐会/Andras Keller指挥布达佩斯交响乐团:巴尔托克中提琴、钢琴与管弦乐协奏曲(普)"},{"start":"12:00","startTime":"20260419120000","stopTime":"20260419132100","program":"爵士乐/巴黎新早晨俱乐部:Raul Midon(普)"},{"start":"13:21","startTime":"20260419132100","stopTime":"20260419141300","program":"爵士乐/巴黎爱乐厅:低音提琴家Avishai Cohen与钢琴家Makoto Ozone(普)"},{"start":"14:13","startTime":"20260419141300","stopTime":"20260419153000","program":"爵士乐/巴黎雅典娜剧院:钢琴家Yaron Herman(普)"},{"start":"15:30","startTime":"20260419153000","stopTime":"20260419193900","program":"歌剧/苏黎世歌剧院:华格纳《齐格菲》(普)"},{"start":"19:39","startTime":"20260419193900","stopTime":"20260419200000","program":"InterMezzo 爱乐间奏(普)"},{"start":"20:00","startTime":"20260419200000","stopTime":"20260419213000","program":"音乐会/Joshua Weilerstein指挥里耳交响乐团:佩萍、杜蒂耶与法朗克作品(普)"},{"start":"21:30","startTime":"20260419213000","stopTime":"20260419230000","program":"音乐会/Christian Thielemann指挥小提琴家A.Hadelich、大提琴家G.Capucon和维也纳爱乐:布拉姆斯作品(普)"},{"start":"23:00","startTime":"20260419230000","stopTime":"20260420000000","program":"艺术舞蹈/捷克国家芭蕾舞团:《审判》Mauro Bigonzetti编舞(普)"},{"start":"00:25","startTime":"20260420002500","stopTime":"20260420015500","program":"歌剧/Vincent Dumestre指挥和谐诗篇乐团:《巴洛克嘉年华》(普)"},{"start":"01:55","startTime":"20260420015500","stopTime":"20260420030000","program":"InterMezzo 爱乐间奏(普)"},{"start":"03:00","startTime":"20260420030000","stopTime":"20260420061400","program":"歌剧/维也纳国立歌剧院:华格纳《唐怀瑟》(普)"},{"start":"06:14","startTime":"20260420061400","stopTime":"20260420073400","program":"音乐会/爱沙尼亚作曲家Arvo Part九十岁生日音乐会(普)"},{"start":"07:34","startTime":"20260420073400","stopTime":"20260420080000","program":"InterMezzo 爱乐间奏(普)"},{"start":"08:00","startTime":"20260420080000","stopTime":"20260420091900","program":"音乐会/Franz Welser-Most指挥维也纳爱乐:亨德密特、理查史特劳斯、荀白克与拉威尔作品(普)"},{"start":"09:19","startTime":"20260420091900","stopTime":"20260420105300","program":"音乐会/Yannick Nezet Seguin指挥钢琴家Y.Bronfman和维也纳爱乐:贝多芬与理查史特劳斯作品(普)"},{"start":"10:53","startTime":"20260420105300","stopTime":"20260420120000","program":"InterMezzo 爱乐间奏(普)"},{"start":"12:00","startTime":"20260420120000","stopTime":"20260420142100","program":"歌剧/维也纳国立歌剧院:普契尼《杜兰朵》(普)"},{"start":"14:21","startTime":"20260420142100","stopTime":"20260420153000","program":"音乐会/日内瓦国际音乐比赛:2024年声乐决赛(纳管弦)(普)"},{"start":"15:30","startTime":"20260420153000","stopTime":"20260420163300","program":"音乐会/Alexandre Bloch指挥钢琴家F.Piemontesi和里耳交响乐团:西贝流士第7号交响曲与贝多芬第5号钢琴协奏曲《皇帝》(普)"},{"start":"16:33","startTime":"20260420163300","stopTime":"20260420173300","program":"音乐会/Alexandre Bloch指挥里耳交响乐团:西贝流士与理查史特劳斯作品(普)"},{"start":"17:33","startTime":"20260420173300","stopTime":"20260420190000","program":"音乐会/大野和士指挥里耳交响乐团:华格纳、理查史特劳斯与萧士塔高维奇作品(普)"},{"start":"19:00","startTime":"20260420190000","stopTime":"20260420201700","program":"音乐会/Christian Thielemann指挥维也纳爱乐:《德意志安魂曲》(普)"},{"start":"20:17","startTime":"20260420201700","stopTime":"20260420213600","program":"音乐会/Christian Thielemann指挥女中音E.Garanca与维也纳爱乐演唱布拉姆斯、布鲁克纳作品(普)"},{"start":"21:36","startTime":"20260420213600","stopTime":"20260420230000","program":"InterMezzo 爱乐间奏(普)"},{"start":"23:00","startTime":"20260420230000","stopTime":"20260421000000","program":"爵士乐/巴黎新早晨俱乐部:Raul Midon(普)"},{"start":"00:21","startTime":"20260421002100","stopTime":"20260421011300","program":"爵士乐/巴黎爱乐厅:低音提琴家Avishai Cohen与钢琴家Makoto Ozone(普)"},{"start":"01:13","startTime":"20260421011300","stopTime":"20260421021700","program":"爵士乐/巴黎雅典娜剧院:钢琴家Yaron Herman(普)"},{"start":"02:17","startTime":"20260421021700","stopTime":"20260421030000","program":"InterMezzo 爱乐间奏(普)"},{"start":"03:00","startTime":"20260421030000","stopTime":"20260421042500","program":"艺术舞蹈/捷克国家芭蕾舞团:《审判》Mauro Bigonzetti编舞(普)"},{"start":"04:25","startTime":"20260421042500","stopTime":"20260421060000","program":"歌剧/Vincent Dumestre指挥和谐诗篇乐团:《巴洛克嘉年华》(普)"},{"start":"06:00","startTime":"20260421060000","stopTime":"20260421070100","program":"音乐会/辛格-伯利尼亚克基金会:钢琴家Lucas Debargue演奏佛瑞即兴曲等作品(普)"},{"start":"07:01","startTime":"20260421070100","stopTime":"20260421080000","program":"InterMezzo 爱乐间奏(普)"},{"start":"08:00","startTime":"20260421080000","stopTime":"20260421092100","program":"爵士乐/巴黎新早晨俱乐部:Raul Midon(普)"},{"start":"09:21","startTime":"20260421092100","stopTime":"20260421101300","program":"爵士乐/巴黎爱乐厅:低音提琴家Avishai Cohen与钢琴家Makoto Ozone(普)"},{"start":"10:13","startTime":"20260421101300","stopTime":"20260421111700","program":"爵士乐/巴黎雅典娜剧院:钢琴家Yaron Herman(普)"},{"start":"11:17","startTime":"20260421111700","stopTime":"20260421120000","program":"InterMezzo 爱乐间奏(普)"},{"start":"12:00","startTime":"20260421120000","stopTime":"20260421131700","program":"音乐会/Christian Thielemann指挥维也纳爱乐:《德意志安魂曲》(普)"},{"start":"13:17","startTime":"20260421131700","stopTime":"20260421143600","program":"音乐会/Christian Thielemann指挥女中音E.Garanca与维也纳爱乐演唱布拉姆斯、布鲁克纳作品(普)"},{"start":"14:36","startTime":"20260421143600","stopTime":"20260421153000","program":"InterMezzo 爱乐间奏(普)"},{"start":"15:30","startTime":"20260421153000","stopTime":"20260421165500","program":"艺术舞蹈/捷克国家芭蕾舞团:《审判》Mauro Bigonzetti编舞(普)"},{"start":"16:55","startTime":"20260421165500","stopTime":"20260421182500","program":"歌剧/Vincent Dumestre指挥和谐诗篇乐团:《巴洛克嘉年华》(普)"},{"start":"18:25","startTime":"20260421182500","stopTime":"20260421190000","program":"InterMezzo 爱乐间奏(普)"},{"start":"19:00","startTime":"20260421190000","stopTime":"20260421204900","program":"音乐会/Andris Nelsons指挥维也纳爱乐:柏格与马勒作品(普)"},{"start":"20:49","startTime":"20260421204900","stopTime":"20260421215200","program":"音乐会/萨尔兹堡音乐节:Yannick Nezet Seguin指挥钢琴家D.Trifonov和维也纳爱乐演奏贝多芬第1号钢琴协奏曲与白辽士《幻想》交响曲(普)"},{"start":"21:52","startTime":"20260421215200","stopTime":"20260421230000","program":"InterMezzo 爱乐间奏(普)"},{"start":"23:00","startTime":"20260421230000","stopTime":"20260422000000","program":"歌剧/维也纳国立歌剧院:华格纳《唐怀瑟》(普)"},{"start":"02:14","startTime":"20260422021400","stopTime":"20260422030000","program":"InterMezzo 爱乐间奏(普)"},{"start":"03:00","startTime":"20260422030000","stopTime":"20260422042400","program":"音乐会/Christian Thielemann指挥小提琴家A.Hadelich、大提琴家G.Capucon和维也纳爱乐:布拉姆斯作品(普)"},{"start":"04:24","startTime":"20260422042400","stopTime":"20260422060000","program":"音乐会/Joshua Weilerstein指挥里耳交响乐团:佩萍、杜蒂耶与法朗克作品(普)"},{"start":"06:00","startTime":"20260422060000","stopTime":"20260422070100","program":"音乐会/辛格-伯利尼亚克基金会:钢琴家Lucas Debargue演奏佛瑞前奏曲等作品(普)"},{"start":"07:01","startTime":"20260422070100","stopTime":"20260422080000","program":"InterMezzo 爱乐间奏(普)"},{"start":"08:00","startTime":"20260422080000","stopTime":"20260422092500","program":"艺术舞蹈/捷克国家芭蕾舞团:《审判》Mauro Bigonzetti编舞(普)"},{"start":"09:25","startTime":"20260422092500","stopTime":"20260422105500","program":"歌剧/Vincent Dumestre指挥和谐诗篇乐团:《巴洛克嘉年华》(普)"},{"start":"10:55","startTime":"20260422105500","stopTime":"20260422113000","program":"InterMezzo 爱乐间奏(普)"},{"start":"11:30","startTime":"20260422113000","stopTime":"20260422153000","program":"歌剧/苏黎世歌剧院:华格纳《女武神》(普)"},{"start":"15:30","startTime":"20260422153000","stopTime":"20260422164900","program":"音乐会/Franz Welser-Most指挥维也纳爱乐:亨德密特、理查史特劳斯、荀白克与拉威尔作品(普)"},{"start":"16:49","startTime":"20260422164900","stopTime":"20260422182300","program":"音乐会/Yannick Nezet Seguin指挥钢琴家Y.Bronfman和维也纳爱乐:贝多芬与理查史特劳斯作品(普)"},{"start":"18:23","startTime":"20260422182300","stopTime":"20260422190000","program":"InterMezzo 爱乐间奏(普)"},{"start":"19:00","startTime":"20260422190000","stopTime":"20260422212100","program":"歌剧/维也纳国立歌剧院:普契尼《杜兰朵》(普)"},{"start":"21:21","startTime":"20260422212100","stopTime":"20260422222500","program":"音乐会/Alexandre Bloch指挥钢琴家F.Piemontesi和里耳交响乐团:西贝流士第7号交响曲与贝多芬第5号钢琴协奏曲《皇帝》(普)"},{"start":"22:25","startTime":"20260422222500","stopTime":"20260422230000","program":"InterMezzo 爱乐间奏(普)"},{"start":"23:00","startTime":"20260422230000","stopTime":"20260423000000","program":"音乐会/Alexandre Bloch指挥里耳交响乐团:西贝流士与理查史特劳斯作品(普)"},{"start":"00:00","startTime":"20260423000000","stopTime":"20260423011500","program":"音乐会/大野和士指挥里耳交响乐团:华格纳、理查史特劳斯与萧士塔高维奇作品(普)"},{"start":"01:15","startTime":"20260423011500","stopTime":"20260423024700","program":"音乐会/Andras Keller指挥布达佩斯交响乐团:巴尔托克中提琴、钢琴与管弦乐协奏曲(普)"},{"start":"02:47","startTime":"20260423024700","stopTime":"20260423030000","program":"InterMezzo 爱乐间奏(普)"},{"start":"03:00","startTime":"20260423030000","stopTime":"20260423042100","program":"爵士乐/巴黎新早晨俱乐部:Raul Midon(普)"},{"start":"04:21","startTime":"20260423042100","stopTime":"20260423051300","program":"爵士乐/巴黎爱乐厅:低音提琴家Avishai Cohen与钢琴家Makoto Ozone(普)"},{"start":"05:13","startTime":"20260423051300","stopTime":"20260423061700","program":"爵士乐/巴黎雅典娜剧院:钢琴家Yaron Herman(普)"},{"start":"06:17","startTime":"20260423061700","stopTime":"20260423080000","program":"音乐会/Christian Thielemann指挥钢琴家I.Levit和维也纳爱乐:布拉姆斯第1号钢琴协奏曲与第2号交响曲(普)"},{"start":"08:00","startTime":"20260423080000","stopTime":"20260423093500","program":"音乐会/Christian Thielemann指挥钢琴家I.Levit和维也纳爱乐:布拉姆斯第2号钢琴协奏曲与第3号交响曲(普)"},{"start":"09:35","startTime":"20260423093500","stopTime":"20260423111800","program":"音乐会/大提琴家Jean-Guihen Queyras、中提琴家Tabea Zimmermann和贝尔琪亚四重奏团演奏布拉姆斯第1、2号弦乐六重奏(普)"},{"start":"11:18","startTime":"20260423111800","stopTime":"20260423120000","program":"InterMezzo 爱乐间奏(普)"},{"start":"12:00","startTime":"20260423120000","stopTime":"20260423132500","program":"艺术舞蹈/捷克国家芭蕾舞团:《审判》Mauro Bigonzetti编舞(普)"},{"start":"13:25","startTime":"20260423132500","stopTime":"20260423145500","program":"歌剧/Vincent Dumestre指挥和谐诗篇乐团:《巴洛克嘉年华》(普)"},{"start":"14:55","startTime":"20260423145500","stopTime":"20260423153000","program":"InterMezzo 爱乐间奏(普)"},{"start":"15:30","startTime":"20260423153000","stopTime":"20260423165100","program":"爵士乐/巴黎新早晨俱乐部:Raul Midon(普)"},{"start":"16:51","startTime":"20260423165100","stopTime":"20260423174300","program":"爵士乐/巴黎爱乐厅:低音提琴家Avishai Cohen与钢琴家Makoto Ozone(普)"},{"start":"17:43","startTime":"20260423174300","stopTime":"20260423184700","program":"爵士乐/巴黎雅典娜剧院:钢琴家Yaron Herman(普)"},{"start":"18:47","startTime":"20260423184700","stopTime":"20260423190000","program":"InterMezzo 爱乐间奏(普)"},{"start":"19:00","startTime":"20260423190000","stopTime":"20260423230000","program":"歌剧/苏黎世歌剧院:华格纳《女武神》(普)"},{"start":"23:00","startTime":"20260423230000","stopTime":"20260424001900","program":"音乐会/Franz Welser-Most指挥维也纳爱乐:亨德密特、理查史特劳斯、荀白克与拉威尔作品(普)"},{"start":"00:19","startTime":"20260424001900","stopTime":"20260424015300","program":"音乐会/Yannick Nezet Seguin指挥钢琴家Y.Bronfman和维也纳爱乐:贝多芬与理查史特劳斯作品(普)"},{"start":"01:53","startTime":"20260424015300","stopTime":"20260424030000","program":"InterMezzo 爱乐间奏(普)"},{"start":"03:00","startTime":"20260424030000","stopTime":"20260424040300","program":"音乐会/Alexandre Bloch指挥钢琴家F.Piemontesi和里耳交响乐团:西贝流士第7号交响曲与贝多芬第5号钢琴协奏曲《皇帝》(普)"},{"start":"04:03","startTime":"20260424040300","stopTime":"20260424050300","program":"音乐会/Alexandre Bloch指挥里耳交响乐团:西贝流士与理查史特劳斯作品(普)"},{"start":"05:03","startTime":"20260424050300","stopTime":"20260424061900","program":"音乐会/大野和士指挥里耳交响乐团:华格纳、理查史特劳斯与萧士塔高维奇作品(普)"},{"start":"06:19","startTime":"20260424061900","stopTime":"20260424080800","program":"音乐会/弗罗茨瓦夫音乐节:Christoph Eschenbach指挥NFM弗罗茨瓦夫爱乐演奏布鲁克纳作品(普)"},{"start":"08:08","startTime":"20260424080800","stopTime":"20260424120400","program":"歌剧/苏黎世歌剧院:华格纳《女武神》(普)"},{"start":"12:04","startTime":"20260424120400","stopTime":"20260424135400","program":"音乐会/Andris Nelsons指挥维也纳爱乐:柏格与马勒作品(普)"},{"start":"13:54","startTime":"20260424135400","stopTime":"20260424145600","program":"音乐会/萨尔兹堡音乐节:Yannick Nezet Seguin指挥钢琴家D.Trifonov和维也纳爱乐演奏贝多芬第1号钢琴协奏曲与白辽士《幻想》交响曲(普)"},{"start":"14:56","startTime":"20260424145600","stopTime":"20260424153000","program":"InterMezzo 爱乐间奏(普)"},{"start":"15:30","startTime":"20260424153000","stopTime":"20260424184400","program":"歌剧/维也纳国立歌剧院:华格纳《唐怀瑟》(普)"},{"start":"18:44","startTime":"20260424184400","stopTime":"20260424190000","program":"InterMezzo 爱乐间奏(普)"},{"start":"19:00","startTime":"20260424190000","stopTime":"20260424202500","program":"艺术舞蹈/捷克国家芭蕾舞团:《审判》Mauro Bigonzetti编舞(普)"},{"start":"20:25","startTime":"20260424202500","stopTime":"20260424222600","program":"音乐会/2025日内瓦国际中提琴比赛决赛(普)"},{"start":"22:26","startTime":"20260424222600","stopTime":"20260424230000","program":"InterMezzo 爱乐间奏(普)"},{"start":"23:00","startTime":"20260424230000","stopTime":"20260425004100","program":"音乐会/Christian Thielemann指挥钢琴家I.Levit和维也纳爱乐:布拉姆斯第1号钢琴协奏曲与第2号交响曲(普)"},{"start":"00:41","startTime":"20260425004100","stopTime":"20260425021600","program":"音乐会/Christian Thielemann指挥钢琴家I.Levit和维也纳爱乐:布拉姆斯第2号钢琴协奏曲与第3号交响曲(普)"},{"start":"02:16","startTime":"20260425021600","stopTime":"20260425030000","program":"InterMezzo 爱乐间奏(普)"},{"start":"03:00","startTime":"20260425030000","stopTime":"20260425070900","program":"歌剧/苏黎世歌剧院:华格纳《齐格菲》(普)"},{"start":"07:09","startTime":"20260425070900","stopTime":"20260425081200","program":"音乐会/萨尔兹堡音乐节:Yannick Nezet Seguin指挥钢琴家D.Trifonov和维也纳爱乐演奏贝多芬第1号钢琴协奏曲与白辽士《幻想》交响曲(普)"},{"start":"08:12","startTime":"20260425081200","stopTime":"20260425094700","program":"音乐会/Yannick Nezet Seguin指挥钢琴家Y.Bronfman和维也纳爱乐:贝多芬与理查史特劳斯作品(普)"},{"start":"09:47","startTime":"20260425094700","stopTime":"20260425110600","program":"音乐会/Franz Welser-Most指挥维也纳爱乐:亨德密特、理查史特劳斯、荀白克与拉威尔作品(普)"},{"start":"11:06","startTime":"20260425110600","stopTime":"20260425113000","program":"InterMezzo 爱乐间奏(普)"},{"start":"11:30","startTime":"20260425113000","stopTime":"20260425132500","program":"音乐会/Antonio Pappano爵士指挥小提琴家V.Frang和伦敦交响乐团:艾尔加小提琴协奏曲与霍尔斯特《行星》(普)"},{"start":"13:25","startTime":"20260425132500","stopTime":"20260425153000","program":"音乐会/Andris Nelsons指挥维也纳爱乐:柏格与马勒作品(普)"},{"start":"15:30","startTime":"20260425153000","stopTime":"20260425171100","program":"音乐会/Christian Thielemann指挥钢琴家I.Levit和维也纳爱乐:布拉姆斯第1号钢琴协奏曲与第2号交响曲(普)"},{"start":"17:11","startTime":"20260425171100","stopTime":"20260425184600","program":"音乐会/Christian Thielemann指挥钢琴家I.Levit和维也纳爱乐:布拉姆斯第2号钢琴协奏曲与第3号交响曲(普)"},{"start":"18:46","startTime":"20260425184600","stopTime":"20260425190000","program":"InterMezzo 爱乐间奏(普)"},{"start":"19:00","startTime":"20260425190000","stopTime":"20260425203400","program":"爵士乐/乌德琴手Anouar Brahem、钢琴家Django Bates、低音提琴手Dave Holland和大提琴家Anja Lechner:《最后一片天空之后》(普)"},{"start":"20:34","startTime":"20260425203400","stopTime":"20260425213900","program":"爵士乐/巴黎爱乐厅:Avishai Cohen四重奏团(普)"},{"start":"21:39","startTime":"20260425213900","stopTime":"20260425221500","program":"InterMezzo 爱乐间奏(普)"},{"start":"22:15","startTime":"20260425221500","stopTime":"20260426030000","program":"歌剧/苏黎世歌剧院:华格纳《诸神的黄昏》(普)"},{"start":"03:00","startTime":"20260426030000","stopTime":"20260426041900","program":"音乐会/Christian Thielemann指挥女中音E.Garanca与维也纳爱乐演唱布拉姆斯、布鲁克纳作品(普)"},{"start":"04:19","startTime":"20260426041900","stopTime":"20260426060000","program":"音乐会/Christian Thielemann指挥维也纳爱乐:《德意志安魂曲》(普)"},{"start":"06:00","startTime":"20260426060000","stopTime":"20260426073100","program":"音乐会/Lahav Shani指挥小提琴家A.Mutter和慕尼黑爱乐:巴哈小提琴管弦乐协奏曲与布鲁克纳第9号交响曲(普)"},{"start":"07:31","startTime":"20260426073100","stopTime":"20260426080000","program":"InterMezzo 爱乐间奏(普)"},{"start":"08:00","startTime":"20260426080000","stopTime":"20260426111400","program":"歌剧/维也纳国立歌剧院:华格纳《唐怀瑟》(普)"},{"start":"11:14","startTime":"20260426111400","stopTime":"20260426113000","program":"InterMezzo 爱乐间奏(普)"},{"start":"11:30","startTime":"20260426113000","stopTime":"20260426130400","program":"爵士乐/乌德琴手Anouar Brahem、钢琴家Django Bates、低音提琴手Dave Holland和大提琴家Anja Lechner:《最后一片天空之后》(普)"},{"start":"13:04","startTime":"20260426130400","stopTime":"20260426141000","program":"爵士乐/巴黎爱乐厅:Avishai Cohen四重奏团(普)"},{"start":"14:10","startTime":"20260426141000","stopTime":"20260426190000","program":"歌剧/苏黎世歌剧院:华格纳《诸神的黄昏》(普)"},{"start":"19:00","startTime":"20260426190000","stopTime":"20260426200200","program":"音乐会/萨尔兹堡音乐节:Yannick Nezet Seguin指挥钢琴家D.Trifonov和维也纳爱乐演奏贝多芬第1号钢琴协奏曲与白辽士《幻想》交响曲(普)"},{"start":"20:02","startTime":"20260426200200","stopTime":"20260426215200","program":"音乐会/Andris Nelsons指挥维也纳爱乐:柏格与马勒作品(普)"},{"start":"21:52","startTime":"20260426215200","stopTime":"20260426230000","program":"InterMezzo 爱乐间奏(普)"},{"start":"23:00","startTime":"20260426230000","stopTime":"20260427001500","program":"艺术舞蹈/捷克国家芭蕾舞团:《一千零一夜》(普)"},{"start":"00:15","startTime":"20260427001500","stopTime":"20260427010100","program":"音乐会/Esa Pekka Salonen指挥钢琴家J.Thibaudet和旧金山交响乐团:史克里亚宾《普罗米修斯-火之诗》(普)"},{"start":"01:01","startTime":"20260427010100","stopTime":"20260427030000","program":"音乐会/Tarmo Peltokoski指挥土鲁斯管弦乐团:潘德列茨基、萧邦与卢托斯瓦夫斯基作品(普)"},{"start":"03:00","startTime":"20260427030000","stopTime":"20260427043000","program":"音乐会/Daniel Harding指挥克里夫兰交响乐团:布列顿《战争安魂曲》(普)"},{"start":"04:30","startTime":"20260427043000","stopTime":"20260427070400","program":"歌剧/维也纳国立歌剧院:普契尼《杜兰朵》(普)"},{"start":"07:04","startTime":"20260427070400","stopTime":"20260427080000","program":"InterMezzo 爱乐间奏(普)"},{"start":"08:00","startTime":"20260427080000","stopTime":"20260427092400","program":"音乐会/Christian Thielemann指挥小提琴家A.Hadelich、大提琴家G.Capucon和维也纳爱乐:布拉姆斯作品(普)"},{"start":"09:24","startTime":"20260427092400","stopTime":"20260427105400","program":"音乐会/Joshua Weilerstein指挥里耳交响乐团:佩萍、杜蒂耶与法朗克作品(普)"},{"start":"10:54","startTime":"20260427105400","stopTime":"20260427120000","program":"InterMezzo 爱乐间奏(普)"},{"start":"12:00","startTime":"20260427120000","stopTime":"20260427151400","program":"歌剧/维也纳国立歌剧院:华格纳《唐怀瑟》(普)"},{"start":"15:14","startTime":"20260427151400","stopTime":"20260427153000","program":"InterMezzo 爱乐间奏(普)"},{"start":"15:30","startTime":"20260427153000","stopTime":"20260427170400","program":"音乐会/Yannick Nezet Seguin指挥钢琴家Y.Bronfman和维也纳爱乐:贝多芬与理查史特劳斯作品(普)"},{"start":"17:04","startTime":"20260427170400","stopTime":"20260427182300","program":"音乐会/Franz Welser-Most指挥维也纳爱乐:亨德密特、理查史特劳斯、荀白克与拉威尔作品(普)"},{"start":"18:23","startTime":"20260427182300","stopTime":"20260427190000","program":"InterMezzo 爱乐间奏(普)"},{"start":"19:00","startTime":"20260427190000","stopTime":"20260427204100","program":"音乐会/Christian Thielemann指挥钢琴家I.Levit和维也纳爱乐:布拉姆斯第1号钢琴协奏曲与第2号交响曲(普)"},{"start":"20:41","startTime":"20260427204100","stopTime":"20260427221600","program":"音乐会/Christian Thielemann指挥钢琴家I.Levit和维也纳爱乐:布拉姆斯第2号钢琴协奏曲与第3号交响曲(普)"},{"start":"22:16","startTime":"20260427221600","stopTime":"20260427230000","program":"InterMezzo 爱乐间奏(普)"},{"start":"23:00","startTime":"20260427230000","stopTime":"20260427234500","program":"音乐会/Esa Pekka Salonen指挥钢琴家J.Thibaudet和旧金山交响乐团:史克里亚宾《普罗米修斯-火之诗》(普)"},{"start":"23:45","startTime":"20260427234500","stopTime":"20260428005100","program":"爵士乐/巴黎爱乐厅:Avishai Cohen四重奏团(普)"},{"start":"00:51","startTime":"20260428005100","stopTime":"20260428030000","program":"爵士乐/乌德琴手Anouar Brahem、钢琴家Django Bates、低音提琴手Dave Holland和大提琴家Anja Lechner:《最后一片天空之后》(普)"},{"start":"03:00","startTime":"20260428030000","stopTime":"20260428041500","program":"艺术舞蹈/捷克国家芭蕾舞团:《一千零一夜》(普)"},{"start":"04:15","startTime":"20260428041500","stopTime":"20260428060000","program":"音乐会/Tarmo Peltokoski指挥土鲁斯管弦乐团:潘德列茨基、萧邦与卢托斯瓦夫斯基作品(普)"},{"start":"06:00","startTime":"20260428060000","stopTime":"20260428074800","program":"音乐会/弗罗茨瓦夫音乐节:Christoph Eschenbach指挥NFM弗罗茨瓦夫爱乐演奏布鲁克纳作品(普)"},{"start":"07:48","startTime":"20260428074800","stopTime":"20260428080000","program":"InterMezzo 爱乐间奏(普)"},{"start":"08:00","startTime":"20260428080000","stopTime":"20260428093400","program":"爵士乐/乌德琴手Anouar Brahem、钢琴家Django Bates、低音提琴手Dave Holland和大提琴家Anja Lechner:《最后一片天空之后》(普)"},{"start":"09:34","startTime":"20260428093400","stopTime":"20260428103900","program":"爵士乐/巴黎爱乐厅:Avishai Cohen四重奏团(普)"},{"start":"10:39","startTime":"20260428103900","stopTime":"20260428120000","program":"音乐会/Joana Mallwitz指挥柏林音乐厅管弦乐团:莫札特《魔笛》序曲与柴可夫斯基第6号交响曲《悲怆》(普)"},{"start":"12:00","startTime":"20260428120000","stopTime":"20260428134100","program":"音乐会/Christian Thielemann指挥钢琴家I.Levit和维也纳爱乐:布拉姆斯第1号钢琴协奏曲与第2号交响曲(普)"},{"start":"13:41","startTime":"20260428134100","stopTime":"20260428151600","program":"音乐会/Christian Thielemann指挥钢琴家I.Levit和维也纳爱乐:布拉姆斯第2号钢琴协奏曲与第3号交响曲(普)"},{"start":"15:16","startTime":"20260428151600","stopTime":"20260428153000","program":"InterMezzo 爱乐间奏(普)"},{"start":"15:30","startTime":"20260428153000","stopTime":"20260428164500","program":"艺术舞蹈/捷克国家芭蕾舞团:《一千零一夜》(普)"},{"start":"16:45","startTime":"20260428164500","stopTime":"20260428181500","program":"音乐会/Tarmo Peltokoski指挥土鲁斯管弦乐团:潘德列茨基、萧邦与卢托斯瓦夫斯基作品(普)"},{"start":"18:15","startTime":"20260428181500","stopTime":"20260428190000","program":"InterMezzo 爱乐间奏(普)"},{"start":"19:00","startTime":"20260428190000","stopTime":"20260428200300","program":"音乐会/Alexandre Bloch指挥钢琴家F.Piemontesi和里耳交响乐团:西贝流士第7号交响曲与贝多芬第5号钢琴协奏曲《皇帝》(普)"},{"start":"20:03","startTime":"20260428200300","stopTime":"20260428210300","program":"音乐会/Alexandre Bloch指挥里耳交响乐团:西贝流士与理查史特劳斯作品(普)"},{"start":"21:03","startTime":"20260428210300","stopTime":"20260428223000","program":"音乐会/大野和士指挥里耳交响乐团:华格纳、理查史特劳斯与萧士塔高维奇作品(普)"},{"start":"22:30","startTime":"20260428223000","stopTime":"20260429005100","program":"歌剧/维也纳国立歌剧院:普契尼《杜兰朵》(普)"},{"start":"00:51","startTime":"20260429005100","stopTime":"20260429030000","program":"音乐会/路易威登艺术中心:钢琴家Arcadi Volodos演奏舒伯特第17号钢琴奏鸣曲与舒曼幻想曲、《儿时情景》(普)"},{"start":"03:00","startTime":"20260429030000","stopTime":"20260429040200","program":"音乐会/萨尔兹堡音乐节:Yannick Nezet Seguin指挥钢琴家D.Trifonov和维也纳爱乐演奏贝多芬第1号钢琴协奏曲与白辽士《幻想》交响曲(普)"},{"start":"04:02","startTime":"20260429040200","stopTime":"20260429060000","program":"音乐会/Andris Nelsons指挥维也纳爱乐:柏格与马勒作品(普)"},{"start":"06:00","startTime":"20260429060000","stopTime":"20260429070100","program":"音乐会/辛格-伯利尼亚克基金会:钢琴家Lucas Debargue演奏佛瑞即兴曲等作品(普)"},{"start":"07:01","startTime":"20260429070100","stopTime":"20260429080000","program":"InterMezzo 爱乐间奏(普)"},{"start":"08:00","startTime":"20260429080000","stopTime":"20260429091500","program":"艺术舞蹈/捷克国家芭蕾舞团:《一千零一夜》(普)"},{"start":"09:15","startTime":"20260429091500","stopTime":"20260429104500","program":"音乐会/Tarmo Peltokoski指挥土鲁斯管弦乐团:潘德列茨基、萧邦与卢托斯瓦夫斯基作品(普)"},{"start":"10:45","startTime":"20260429104500","stopTime":"20260429110000","program":"InterMezzo 爱乐间奏(普)"},{"start":"11:00","startTime":"20260429110000","stopTime":"20260429153000","program":"歌剧/苏黎世歌剧院:华格纳《齐格菲》(普)"},{"start":"15:30","startTime":"20260429153000","stopTime":"20260429165400","program":"音乐会/Christian Thielemann指挥小提琴家A.Hadelich、大提琴家G.Capucon和维也纳爱乐:布拉姆斯作品(普)"},{"start":"16:54","startTime":"20260429165400","stopTime":"20260429182400","program":"音乐会/Joshua Weilerstein指挥里耳交响乐团:佩萍、杜蒂耶与法朗克作品(普)"},{"start":"18:24","startTime":"20260429182400","stopTime":"20260429190000","program":"InterMezzo 爱乐间奏(普)"},{"start":"19:00","startTime":"20260429190000","stopTime":"20260429221400","program":"歌剧/维也纳国立歌剧院:华格纳《唐怀瑟》(普)"},{"start":"22:14","startTime":"20260429221400","stopTime":"20260429224500","program":"InterMezzo 爱乐间奏(普)"},{"start":"22:45","startTime":"20260429224500","stopTime":"20260430000000","program":"音乐会/Yannick Nezet Seguin指挥钢琴家Y.Bronfman和维也纳爱乐:贝多芬与理查史特劳斯作品(普)"}]