[{"start":"00:00","startTime":"20260409000000","stopTime":"20260409003100","program":"寰宇视野(98)"},{"start":"00:31","startTime":"20260409003100","stopTime":"20260409012700","program":"全景自然(98):猎豹家族传奇(3)"},{"start":"01:27","startTime":"20260409012700","stopTime":"20260409022300","program":"魅力万象:自然回响-猴子的故事"},{"start":"02:23","startTime":"20260409022300","stopTime":"20260409025300","program":"活力·源(98):原味西藏(1)"},{"start":"02:53","startTime":"20260409025300","stopTime":"20260409035400","program":"特别呈现(98):祁连山·秘境家园"},{"start":"03:54","startTime":"20260409035400","stopTime":"20260409041100","program":"9视频(98):生命树(8)"},{"start":"04:11","startTime":"20260409041100","stopTime":"20260409044600","program":"活力·源(98):原味西藏(1)"},{"start":"04:46","startTime":"20260409044600","stopTime":"20260409051200","program":"故事中国(91):城市花季(5)"},{"start":"05:12","startTime":"20260409051200","stopTime":"20260409054200","program":"故事中国(91):城市花季(6)"},{"start":"05:42","startTime":"20260409054200","stopTime":"20260409054600","program":"中华人民共和国国歌"},{"start":"05:46","startTime":"20260409054600","stopTime":"20260409064700","program":"全景自然(98):猎豹家族传奇(3)"},{"start":"06:47","startTime":"20260409064700","stopTime":"20260409074300","program":"魅力万象:自然回响-猴子的故事"},{"start":"07:43","startTime":"20260409074300","stopTime":"20260409075900","program":"9视频(98):生命树(8)"},{"start":"07:59","startTime":"20260409075900","stopTime":"20260409083100","program":"活力·源(98):原味西藏(1)"},{"start":"08:31","startTime":"20260409083100","stopTime":"20260409092700","program":"特别呈现(98):祁连山·秘境家园"},{"start":"09:27","startTime":"20260409092700","stopTime":"20260409102600","program":"全景自然(98):猎豹家族传奇(3)"},{"start":"10:26","startTime":"20260409102600","stopTime":"20260409112500","program":"魅力万象:自然回响-猴子的故事"},{"start":"11:25","startTime":"20260409112500","stopTime":"20260409122700","program":"寰宇视野(98)"},{"start":"12:27","startTime":"20260409122700","stopTime":"20260409133100","program":"特别呈现(98):祁连山·秘境家园"},{"start":"13:31","startTime":"20260409133100","stopTime":"20260409143000","program":"全景自然(98):猎豹家族传奇(3)"},{"start":"14:30","startTime":"20260409143000","stopTime":"20260409153000","program":"魅力万象:自然回响-猴子的故事"},{"start":"15:30","startTime":"20260409153000","stopTime":"20260409155700","program":"故事中国(91):城市花季(5)"},{"start":"15:57","startTime":"20260409155700","stopTime":"20260409162900","program":"故事中国(91):城市花季(6)"},{"start":"16:29","startTime":"20260409162900","stopTime":"20260409172800","program":"寰宇视野(98)"},{"start":"17:28","startTime":"20260409172800","stopTime":"20260409182700","program":"全景自然(99):卡塔维国家公园(1)"},{"start":"18:27","startTime":"20260409182700","stopTime":"20260409192700","program":"魅力万象(99):卡塔维国家公园(2)"},{"start":"19:27","startTime":"20260409192700","stopTime":"20260409200000","program":"活力·源(99):原味西藏(2)"},{"start":"20:00","startTime":"20260409200000","stopTime":"20260409202700","program":"特别呈现:跨越太平洋的相聚(1)"},{"start":"20:27","startTime":"20260409202700","stopTime":"20260409210000","program":"特别呈现:跨越太平洋的相聚(2)"},{"start":"21:00","startTime":"20260409210000","stopTime":"20260409220400","program":"寰宇视野(99):美洲豹海岸"},{"start":"22:04","startTime":"20260409220400","stopTime":"20260409223100","program":"故事中国(92):城市花季(7)"},{"start":"22:31","startTime":"20260409223100","stopTime":"20260409230600","program":"故事中国(92):城市花季(8)"},{"start":"23:06","startTime":"20260409230600","stopTime":"20260409232700","program":"9视频(99):谁调鼎中味(1)"},{"start":"23:27","startTime":"20260409232700","stopTime":"20260409235959","program":"寰宇视野(99):美洲豹海岸"},{"start":"00:00","startTime":"20260410000000","stopTime":"20260410003100","program":"寰宇视野(99):美洲豹海岸"},{"start":"00:31","startTime":"20260410003100","stopTime":"20260410012700","program":"全景自然(99):卡塔维国家公园(1)"},{"start":"01:27","startTime":"20260410012700","stopTime":"20260410022300","program":"魅力万象(99):卡塔维国家公园(2)"},{"start":"02:23","startTime":"20260410022300","stopTime":"20260410025300","program":"活力·源(99):原味西藏(2)"},{"start":"02:53","startTime":"20260410025300","stopTime":"20260410032000","program":"特别呈现:跨越太平洋的相聚(1)"},{"start":"03:20","startTime":"20260410032000","stopTime":"20260410035400","program":"特别呈现:跨越太平洋的相聚(2)"},{"start":"03:54","startTime":"20260410035400","stopTime":"20260410041100","program":"9视频(99):谁调鼎中味(1)"},{"start":"04:11","startTime":"20260410041100","stopTime":"20260410044600","program":"活力·源(99):原味西藏(2)"},{"start":"04:46","startTime":"20260410044600","stopTime":"20260410051200","program":"故事中国(92):城市花季(7)"},{"start":"05:12","startTime":"20260410051200","stopTime":"20260410054200","program":"故事中国(92):城市花季(8)"},{"start":"05:42","startTime":"20260410054200","stopTime":"20260410054600","program":"中华人民共和国国歌"},{"start":"05:46","startTime":"20260410054600","stopTime":"20260410064700","program":"全景自然(99):卡塔维国家公园(1)"},{"start":"06:47","startTime":"20260410064700","stopTime":"20260410074300","program":"魅力万象(99):卡塔维国家公园(2)"},{"start":"07:43","startTime":"20260410074300","stopTime":"20260410075900","program":"9视频(99):谁调鼎中味(1)"},{"start":"07:59","startTime":"20260410075900","stopTime":"20260410083100","program":"活力·源(99):原味西藏(2)"},{"start":"08:31","startTime":"20260410083100","stopTime":"20260410085800","program":"特别呈现:跨越太平洋的相聚(1)"},{"start":"08:58","startTime":"20260410085800","stopTime":"20260410092700","program":"特别呈现:跨越太平洋的相聚(2)"},{"start":"09:27","startTime":"20260410092700","stopTime":"20260410102600","program":"全景自然(55):冰原漫步(1)"},{"start":"10:26","startTime":"20260410102600","stopTime":"20260410112500","program":"魅力万象(55):冰原漫步(2)"},{"start":"11:25","startTime":"20260410112500","stopTime":"20260410122700","program":"全景自然(72):南美奇趣动物(1)"},{"start":"12:27","startTime":"20260410122700","stopTime":"20260410133100","program":"魅力万象(72):南美奇趣动物(2)"},{"start":"13:31","startTime":"20260410133100","stopTime":"20260410143000","program":"全景自然(73):南美奇趣动物(3)"},{"start":"14:30","startTime":"20260410143000","stopTime":"20260410153000","program":"全景自然(31):狂野五大湖(1)"},{"start":"15:30","startTime":"20260410153000","stopTime":"20260410162900","program":"魅力万象(31):狂野五大湖(2)"},{"start":"16:29","startTime":"20260410162900","stopTime":"20260410172800","program":"全景自然(32):狂野五大湖(3)"},{"start":"17:28","startTime":"20260410172800","stopTime":"20260410182700","program":"全景自然:卡塔维国家公园(3)"},{"start":"18:27","startTime":"20260410182700","stopTime":"20260410192700","program":"魅力万象(100):港海豹的故事"},{"start":"19:27","startTime":"20260410192700","stopTime":"20260410200000","program":"活力·源(100):守望秦岭(1)"},{"start":"20:00","startTime":"20260410200000","stopTime":"20260410210000","program":"特别呈现(100)"},{"start":"21:00","startTime":"20260410210000","stopTime":"20260410220400","program":"寰宇视野(100):棕熊的觅食故事"},{"start":"22:04","startTime":"20260410220400","stopTime":"20260410230600","program":"故事中国:世界遗产漫步·大运河"},{"start":"23:06","startTime":"20260410230600","stopTime":"20260410232700","program":"9视频(100):谁调鼎中味(2)"},{"start":"23:27","startTime":"20260410232700","stopTime":"20260410235959","program":"寰宇视野(100):棕熊的觅食故事"},{"start":"00:00","startTime":"20260411000000","stopTime":"20260411003100","program":"寰宇视野(100):棕熊的觅食故事"},{"start":"00:31","startTime":"20260411003100","stopTime":"20260411012700","program":"全景自然:卡塔维国家公园(3)"},{"start":"01:27","startTime":"20260411012700","stopTime":"20260411022300","program":"魅力万象(100):港海豹的故事"},{"start":"02:23","startTime":"20260411022300","stopTime":"20260411025300","program":"活力·源(100):守望秦岭(1)"},{"start":"02:53","startTime":"20260411025300","stopTime":"20260411035400","program":"特别呈现(100)"},{"start":"03:54","startTime":"20260411035400","stopTime":"20260411041100","program":"9视频(100):谁调鼎中味(2)"},{"start":"04:11","startTime":"20260411041100","stopTime":"20260411044600","program":"活力·源(100):守望秦岭(1)"},{"start":"04:46","startTime":"20260411044600","stopTime":"20260411054200","program":"故事中国:世界遗产漫步·大运河"},{"start":"05:42","startTime":"20260411054200","stopTime":"20260411054600","program":"中华人民共和国国歌"},{"start":"05:46","startTime":"20260411054600","stopTime":"20260411064700","program":"全景自然:卡塔维国家公园(3)"},{"start":"06:47","startTime":"20260411064700","stopTime":"20260411074300","program":"魅力万象(100):港海豹的故事"},{"start":"07:43","startTime":"20260411074300","stopTime":"20260411075900","program":"9视频(100):谁调鼎中味(2)"},{"start":"07:59","startTime":"20260411075900","stopTime":"20260411093300","program":"纪录影院(13):狼之旅"},{"start":"09:33","startTime":"20260411093300","stopTime":"20260411103200","program":"全景自然(44):幼豹启蒙"},{"start":"10:32","startTime":"20260411103200","stopTime":"20260411113100","program":"魅力万象:阿尔贝格山生灵密语"},{"start":"11:31","startTime":"20260411113100","stopTime":"20260411123200","program":"寰宇视野(94):神秘的蛇(1)"},{"start":"12:32","startTime":"20260411123200","stopTime":"20260411133100","program":"寰宇视野(95):神秘的蛇(2)"},{"start":"13:31","startTime":"20260411133100","stopTime":"20260411143000","program":"寰宇视野(96):神秘的蛇(3)"},{"start":"14:30","startTime":"20260411143000","stopTime":"20260411153000","program":"寰宇视野(41):极速猎杀(1)"},{"start":"15:30","startTime":"20260411153000","stopTime":"20260411162900","program":"寰宇视野(42):极速猎杀(2)"},{"start":"16:29","startTime":"20260411162900","stopTime":"20260411172800","program":"寰宇视野(43):极速猎杀(3)"},{"start":"17:28","startTime":"20260411172800","stopTime":"20260411182700","program":"全景自然(101):猎杀倒计时(1)"},{"start":"18:27","startTime":"20260411182700","stopTime":"20260411192700","program":"魅力万象(101):猎杀倒计时(2)"},{"start":"19:27","startTime":"20260411192700","stopTime":"20260411200000","program":"活力·源(101):守望秦岭(2)"},{"start":"20:00","startTime":"20260411200000","stopTime":"20260411210000","program":"特别呈现(101)"},{"start":"21:00","startTime":"20260411210000","stopTime":"20260411220400","program":"寰宇视野:金雕-野性的呼唤(1)"},{"start":"22:04","startTime":"20260411220400","stopTime":"20260411230600","program":"故事中国:世界遗产漫步·大运河"},{"start":"23:06","startTime":"20260411230600","stopTime":"20260411232700","program":"9视频(101):谁调鼎中味(3)"},{"start":"23:27","startTime":"20260411232700","stopTime":"20260411235959","program":"寰宇视野:金雕-野性的呼唤(1)"},{"start":"00:00","startTime":"20260412000000","stopTime":"20260412003100","program":"寰宇视野:金雕-野性的呼唤(1)"},{"start":"00:31","startTime":"20260412003100","stopTime":"20260412012700","program":"全景自然(101):猎杀倒计时(1)"},{"start":"01:27","startTime":"20260412012700","stopTime":"20260412022300","program":"魅力万象(101):猎杀倒计时(2)"},{"start":"02:23","startTime":"20260412022300","stopTime":"20260412025300","program":"活力·源(101):守望秦岭(2)"},{"start":"02:53","startTime":"20260412025300","stopTime":"20260412035400","program":"特别呈现(101)"},{"start":"03:54","startTime":"20260412035400","stopTime":"20260412041100","program":"9视频(101):谁调鼎中味(3)"},{"start":"04:11","startTime":"20260412041100","stopTime":"20260412044600","program":"活力·源(101):守望秦岭(2)"},{"start":"04:46","startTime":"20260412044600","stopTime":"20260412054200","program":"故事中国:世界遗产漫步·大运河"},{"start":"05:42","startTime":"20260412054200","stopTime":"20260412054600","program":"中华人民共和国国歌"},{"start":"05:46","startTime":"20260412054600","stopTime":"20260412064700","program":"全景自然(101):猎杀倒计时(1)"},{"start":"06:47","startTime":"20260412064700","stopTime":"20260412074300","program":"魅力万象(101):猎杀倒计时(2)"},{"start":"07:43","startTime":"20260412074300","stopTime":"20260412075900","program":"9视频(101):谁调鼎中味(3)"},{"start":"07:59","startTime":"20260412075900","stopTime":"20260412083100","program":"活力·源(101):守望秦岭(2)"},{"start":"08:31","startTime":"20260412083100","stopTime":"20260412092700","program":"特别呈现(101)"},{"start":"09:27","startTime":"20260412092700","stopTime":"20260412102600","program":"寰宇视野(4):豹妈妈"},{"start":"10:26","startTime":"20260412102600","stopTime":"20260412112500","program":"寰宇视野(83):狮王塞西尔"},{"start":"11:25","startTime":"20260412112500","stopTime":"20260412122700","program":"全景自然(94):生存绝技(1)"},{"start":"12:27","startTime":"20260412122700","stopTime":"20260412133100","program":"魅力万象(94):生存绝技(2)"},{"start":"13:31","startTime":"20260412133100","stopTime":"20260412143000","program":"全景自然(95):生存绝技(3)"},{"start":"14:30","startTime":"20260412143000","stopTime":"20260412153000","program":"魅力万象(95):生存绝技(4)"},{"start":"15:30","startTime":"20260412153000","stopTime":"20260412162900","program":"全景自然(96):生存绝技(5)"},{"start":"16:29","startTime":"20260412162900","stopTime":"20260412172800","program":"魅力万象(96):生存绝技(6)"},{"start":"17:28","startTime":"20260412172800","stopTime":"20260412182700","program":"全景自然(102):猎杀倒计时(3)"},{"start":"18:27","startTime":"20260412182700","stopTime":"20260412192700","program":"魅力万象(102):猎杀倒计时(4)"},{"start":"19:27","startTime":"20260412192700","stopTime":"20260412200000","program":"活力·源(102):守望秦岭(3)"},{"start":"20:00","startTime":"20260412200000","stopTime":"20260412210000","program":"特别呈现(102)"},{"start":"21:00","startTime":"20260412210000","stopTime":"20260412220400","program":"寰宇视野:金雕-野性的呼唤(2)"},{"start":"22:04","startTime":"20260412220400","stopTime":"20260412233800","program":"纪录影院:北欧高地的动物传奇"},{"start":"23:38","startTime":"20260412233800","stopTime":"20260412235959","program":"9视频(102):谁调鼎中味(4)"},{"start":"00:00","startTime":"20260413000000","stopTime":"20260413010300","program":"寰宇视野:金雕-野性的呼唤(2)"},{"start":"01:03","startTime":"20260413010300","stopTime":"20260413020000","program":"全景自然(102):猎杀倒计时(3)"},{"start":"02:00","startTime":"20260413020000","stopTime":"20260413025700","program":"魅力万象(102):猎杀倒计时(4)"},{"start":"02:57","startTime":"20260413025700","stopTime":"20260413035400","program":"特别呈现(102)"},{"start":"03:54","startTime":"20260413035400","stopTime":"20260413041100","program":"9视频(102):谁调鼎中味(4)"},{"start":"04:11","startTime":"20260413041100","stopTime":"20260413044600","program":"活力·源(102):守望秦岭(3)"},{"start":"04:46","startTime":"20260413044600","stopTime":"20260413054200","program":"故事中国:世界遗产漫步·大运河"},{"start":"05:42","startTime":"20260413054200","stopTime":"20260413054600","program":"中华人民共和国国歌"},{"start":"05:46","startTime":"20260413054600","stopTime":"20260413064700","program":"全景自然(102):猎杀倒计时(3)"},{"start":"06:47","startTime":"20260413064700","stopTime":"20260413074300","program":"魅力万象(102):猎杀倒计时(4)"},{"start":"07:43","startTime":"20260413074300","stopTime":"20260413075900","program":"9视频(102):谁调鼎中味(4)"},{"start":"07:59","startTime":"20260413075900","stopTime":"20260413083100","program":"活力·源(102):守望秦岭(3)"},{"start":"08:31","startTime":"20260413083100","stopTime":"20260413092700","program":"特别呈现(102)"},{"start":"09:27","startTime":"20260413092700","stopTime":"20260413102600","program":"全景自然(102):猎杀倒计时(3)"},{"start":"10:26","startTime":"20260413102600","stopTime":"20260413112500","program":"魅力万象(102):猎杀倒计时(4)"},{"start":"11:25","startTime":"20260413112500","stopTime":"20260413122700","program":"寰宇视野:金雕-野性的呼唤(2)"},{"start":"12:27","startTime":"20260413122700","stopTime":"20260413133100","program":"特别呈现(102)"},{"start":"13:31","startTime":"20260413133100","stopTime":"20260413143000","program":"全景自然(102):猎杀倒计时(3)"},{"start":"14:30","startTime":"20260413143000","stopTime":"20260413153000","program":"魅力万象(102):猎杀倒计时(4)"},{"start":"15:30","startTime":"20260413153000","stopTime":"20260413162900","program":"故事中国:世界遗产漫步·大运河"},{"start":"16:29","startTime":"20260413162900","stopTime":"20260413172800","program":"寰宇视野:金雕-野性的呼唤(2)"},{"start":"17:28","startTime":"20260413172800","stopTime":"20260413182700","program":"全景自然(103):欧洲海洋探秘(1)"},{"start":"18:27","startTime":"20260413182700","stopTime":"20260413192700","program":"魅力万象(103):欧洲海洋探秘(2)"},{"start":"19:27","startTime":"20260413192700","stopTime":"20260413200000","program":"活力·源(103):守望秦岭(4)"},{"start":"20:00","startTime":"20260413200000","stopTime":"20260413210000","program":"特别呈现(103)"},{"start":"21:00","startTime":"20260413210000","stopTime":"20260413220400","program":"寰宇视野(103):虎的传承(1)"},{"start":"22:04","startTime":"20260413220400","stopTime":"20260413230600","program":"故事中国(95):北京往事(1)"},{"start":"23:06","startTime":"20260413230600","stopTime":"20260413232700","program":"9视频:你听见了吗·婚姻篇(1)"},{"start":"23:27","startTime":"20260413232700","stopTime":"20260413235959","program":"寰宇视野(103):虎的传承(1)"},{"start":"00:00","startTime":"20260414000000","stopTime":"20260414003100","program":"寰宇视野(103):虎的传承(1)"},{"start":"00:31","startTime":"20260414003100","stopTime":"20260414012700","program":"全景自然(103):欧洲海洋探秘(1)"},{"start":"01:27","startTime":"20260414012700","stopTime":"20260414022300","program":"魅力万象(103):欧洲海洋探秘(2)"},{"start":"02:23","startTime":"20260414022300","stopTime":"20260414025300","program":"活力·源(103):守望秦岭(4)"},{"start":"02:53","startTime":"20260414025300","stopTime":"20260414035400","program":"特别呈现(103)"},{"start":"03:54","startTime":"20260414035400","stopTime":"20260414041100","program":"9视频:你听见了吗·婚姻篇(1)"},{"start":"04:11","startTime":"20260414041100","stopTime":"20260414044600","program":"活力·源(103):守望秦岭(4)"},{"start":"04:46","startTime":"20260414044600","stopTime":"20260414054200","program":"故事中国(95):北京往事(1)"},{"start":"05:42","startTime":"20260414054200","stopTime":"20260414054600","program":"中华人民共和国国歌"},{"start":"05:46","startTime":"20260414054600","stopTime":"20260414064700","program":"全景自然(103):欧洲海洋探秘(1)"},{"start":"06:47","startTime":"20260414064700","stopTime":"20260414074300","program":"魅力万象(103):欧洲海洋探秘(2)"},{"start":"07:43","startTime":"20260414074300","stopTime":"20260414075900","program":"9视频:你听见了吗·婚姻篇(1)"},{"start":"07:59","startTime":"20260414075900","stopTime":"20260414083100","program":"活力·源(103):守望秦岭(4)"},{"start":"08:31","startTime":"20260414083100","stopTime":"20260414092700","program":"特别呈现(103)"},{"start":"09:27","startTime":"20260414092700","stopTime":"20260414102600","program":"全景自然(103):欧洲海洋探秘(1)"},{"start":"10:26","startTime":"20260414102600","stopTime":"20260414112500","program":"魅力万象(103):欧洲海洋探秘(2)"},{"start":"11:25","startTime":"20260414112500","stopTime":"20260414122700","program":"寰宇视野(103):虎的传承(1)"},{"start":"12:27","startTime":"20260414122700","stopTime":"20260414133100","program":"特别呈现(103)"},{"start":"13:31","startTime":"20260414133100","stopTime":"20260414143000","program":"全景自然(103):欧洲海洋探秘(1)"},{"start":"14:30","startTime":"20260414143000","stopTime":"20260414153000","program":"魅力万象(103):欧洲海洋探秘(2)"},{"start":"15:30","startTime":"20260414153000","stopTime":"20260414162900","program":"故事中国(95):北京往事(1)"},{"start":"16:29","startTime":"20260414162900","stopTime":"20260414172800","program":"寰宇视野(103):虎的传承(1)"},{"start":"17:28","startTime":"20260414172800","stopTime":"20260414182700","program":"全景自然(104):欧洲海洋探秘(3)"},{"start":"18:27","startTime":"20260414182700","stopTime":"20260414192900","program":"魅力万象(104):欧洲海洋探秘(4)"},{"start":"19:29","startTime":"20260414192900","stopTime":"20260414200000","program":"活力·源(104):中老铁路纪行(1)"},{"start":"20:00","startTime":"20260414200000","stopTime":"20260414210000","program":"特别呈现(104)"},{"start":"21:00","startTime":"20260414210000","stopTime":"20260414220400","program":"寰宇视野(104):虎的传承(2)"},{"start":"22:04","startTime":"20260414220400","stopTime":"20260414230600","program":"故事中国(96):北京往事(2)"},{"start":"23:06","startTime":"20260414230600","stopTime":"20260414232700","program":"9视频:你听见了吗·婚姻篇(2)"},{"start":"23:27","startTime":"20260414232700","stopTime":"20260414235959","program":"寰宇视野(104):虎的传承(2)"},{"start":"00:00","startTime":"20260415000000","stopTime":"20260415003100","program":"寰宇视野(104):虎的传承(2)"},{"start":"00:31","startTime":"20260415003100","stopTime":"20260415012700","program":"全景自然(104):欧洲海洋探秘(3)"},{"start":"01:27","startTime":"20260415012700","stopTime":"20260415022300","program":"魅力万象(104):欧洲海洋探秘(4)"},{"start":"02:23","startTime":"20260415022300","stopTime":"20260415025300","program":"活力·源(2):野性的呼唤Ⅱ(1)"},{"start":"02:53","startTime":"20260415025300","stopTime":"20260415035400","program":"特别呈现(104)"},{"start":"03:54","startTime":"20260415035400","stopTime":"20260415041100","program":"9视频:你听见了吗·婚姻篇(2)"},{"start":"04:11","startTime":"20260415041100","stopTime":"20260415044600","program":"活力·源(2):野性的呼唤Ⅱ(1)"},{"start":"04:46","startTime":"20260415044600","stopTime":"20260415054200","program":"故事中国(96):北京往事(2)"},{"start":"05:42","startTime":"20260415054200","stopTime":"20260415054600","program":"中华人民共和国国歌"},{"start":"05:46","startTime":"20260415054600","stopTime":"20260415064700","program":"全景自然(104):欧洲海洋探秘(3)"},{"start":"06:47","startTime":"20260415064700","stopTime":"20260415074300","program":"魅力万象(104):欧洲海洋探秘(4)"},{"start":"07:43","startTime":"20260415074300","stopTime":"20260415075900","program":"9视频:你听见了吗·婚姻篇(2)"},{"start":"07:59","startTime":"20260415075900","stopTime":"20260415083100","program":"活力·源(2):野性的呼唤Ⅱ(1)"},{"start":"08:31","startTime":"20260415083100","stopTime":"20260415092700","program":"特别呈现(104)"},{"start":"09:27","startTime":"20260415092700","stopTime":"20260415102600","program":"全景自然(104):欧洲海洋探秘(3)"},{"start":"10:26","startTime":"20260415102600","stopTime":"20260415112500","program":"魅力万象(104):欧洲海洋探秘(4)"},{"start":"11:25","startTime":"20260415112500","stopTime":"20260415122700","program":"寰宇视野(104):虎的传承(2)"},{"start":"12:27","startTime":"20260415122700","stopTime":"20260415133100","program":"特别呈现(104)"},{"start":"13:31","startTime":"20260415133100","stopTime":"20260415143000","program":"全景自然(104):欧洲海洋探秘(3)"},{"start":"14:30","startTime":"20260415143000","stopTime":"20260415153000","program":"魅力万象(104):欧洲海洋探秘(4)"},{"start":"15:30","startTime":"20260415153000","stopTime":"20260415162900","program":"故事中国(96):北京往事(2)"},{"start":"16:29","startTime":"20260415162900","stopTime":"20260415172800","program":"寰宇视野(104):虎的传承(2)"},{"start":"17:28","startTime":"20260415172800","stopTime":"20260415182700","program":"全景自然:动物生存竞技场(1)"},{"start":"18:27","startTime":"20260415182700","stopTime":"20260415192900","program":"魅力万象:动物生存竞技场(2)"},{"start":"19:29","startTime":"20260415192900","stopTime":"20260415200000","program":"活力·源(105):中老铁路纪行(2)"},{"start":"20:00","startTime":"20260415200000","stopTime":"20260415210000","program":"特别呈现(105):野性传奇(1)"},{"start":"21:00","startTime":"20260415210000","stopTime":"20260415220400","program":"寰宇视野(105):虎的传承(3)"},{"start":"22:04","startTime":"20260415220400","stopTime":"20260415230600","program":"故事中国(97):北京往事(3)"},{"start":"23:06","startTime":"20260415230600","stopTime":"20260415232700","program":"9视频:你听见了吗·婚姻篇(3)"},{"start":"23:27","startTime":"20260415232700","stopTime":"20260415235959","program":"寰宇视野(105):虎的传承(3)"},{"start":"00:00","startTime":"20260416000000","stopTime":"20260416003100","program":"寰宇视野(105):虎的传承(3)"},{"start":"00:31","startTime":"20260416003100","stopTime":"20260416012700","program":"全景自然:动物生存竞技场(1)"},{"start":"01:27","startTime":"20260416012700","stopTime":"20260416022300","program":"魅力万象:动物生存竞技场(2)"},{"start":"02:23","startTime":"20260416022300","stopTime":"20260416025300","program":"活力·源(3)"},{"start":"02:53","startTime":"20260416025300","stopTime":"20260416035400","program":"特别呈现(105):野性传奇(1)"},{"start":"03:54","startTime":"20260416035400","stopTime":"20260416041100","program":"9视频:你听见了吗·婚姻篇(3)"},{"start":"04:11","startTime":"20260416041100","stopTime":"20260416044600","program":"活力·源(3)"},{"start":"04:46","startTime":"20260416044600","stopTime":"20260416054200","program":"故事中国(97):北京往事(3)"},{"start":"05:42","startTime":"20260416054200","stopTime":"20260416054600","program":"中华人民共和国国歌"},{"start":"05:46","startTime":"20260416054600","stopTime":"20260416064700","program":"全景自然:动物生存竞技场(1)"},{"start":"06:47","startTime":"20260416064700","stopTime":"20260416074300","program":"魅力万象:动物生存竞技场(2)"},{"start":"07:43","startTime":"20260416074300","stopTime":"20260416075900","program":"9视频:你听见了吗·婚姻篇(3)"},{"start":"07:59","startTime":"20260416075900","stopTime":"20260416083100","program":"活力·源(3)"},{"start":"08:31","startTime":"20260416083100","stopTime":"20260416092700","program":"特别呈现(105):野性传奇(1)"},{"start":"09:27","startTime":"20260416092700","stopTime":"20260416102600","program":"全景自然:动物生存竞技场(1)"},{"start":"10:26","startTime":"20260416102600","stopTime":"20260416112500","program":"魅力万象:动物生存竞技场(2)"},{"start":"11:25","startTime":"20260416112500","stopTime":"20260416122700","program":"寰宇视野(105):虎的传承(3)"},{"start":"12:27","startTime":"20260416122700","stopTime":"20260416133100","program":"特别呈现(105):野性传奇(1)"},{"start":"13:31","startTime":"20260416133100","stopTime":"20260416143000","program":"全景自然:动物生存竞技场(1)"},{"start":"14:30","startTime":"20260416143000","stopTime":"20260416153000","program":"魅力万象:动物生存竞技场(2)"},{"start":"15:30","startTime":"20260416153000","stopTime":"20260416162900","program":"故事中国(97):北京往事(3)"},{"start":"16:29","startTime":"20260416162900","stopTime":"20260416172800","program":"寰宇视野(105):虎的传承(3)"},{"start":"17:28","startTime":"20260416172800","stopTime":"20260416182700","program":"全景自然(106)"},{"start":"18:27","startTime":"20260416182700","stopTime":"20260416192900","program":"魅力万象(106)"},{"start":"19:29","startTime":"20260416192900","stopTime":"20260416200000","program":"活力·源(106)"},{"start":"20:00","startTime":"20260416200000","stopTime":"20260416210000","program":"特别呈现(106)"},{"start":"21:00","startTime":"20260416210000","stopTime":"20260416220400","program":"寰宇视野(106)"},{"start":"22:04","startTime":"20260416220400","stopTime":"20260416230600","program":"故事中国(98)"},{"start":"23:06","startTime":"20260416230600","stopTime":"20260416232700","program":"9视频(106)"},{"start":"23:27","startTime":"20260416232700","stopTime":"20260416235959","program":"寰宇视野(106)"},{"start":"00:00","startTime":"20260417000000","stopTime":"20260417003100","program":"寰宇视野(106)"},{"start":"00:31","startTime":"20260417003100","stopTime":"20260417012700","program":"全景自然(106)"},{"start":"01:27","startTime":"20260417012700","stopTime":"20260417022300","program":"魅力万象(106)"},{"start":"02:23","startTime":"20260417022300","stopTime":"20260417025300","program":"活力·源(4)"},{"start":"02:53","startTime":"20260417025300","stopTime":"20260417035400","program":"特别呈现(106)"},{"start":"03:54","startTime":"20260417035400","stopTime":"20260417041100","program":"9视频(106)"},{"start":"04:11","startTime":"20260417041100","stopTime":"20260417044600","program":"活力·源(4)"},{"start":"04:46","startTime":"20260417044600","stopTime":"20260417054200","program":"故事中国(98)"},{"start":"05:42","startTime":"20260417054200","stopTime":"20260417054600","program":"中华人民共和国国歌"},{"start":"05:46","startTime":"20260417054600","stopTime":"20260417064700","program":"全景自然(106)"},{"start":"06:47","startTime":"20260417064700","stopTime":"20260417074300","program":"魅力万象(106)"},{"start":"07:43","startTime":"20260417074300","stopTime":"20260417075900","program":"9视频(106)"},{"start":"07:59","startTime":"20260417075900","stopTime":"20260417083100","program":"活力·源(4)"},{"start":"08:31","startTime":"20260417083100","stopTime":"20260417092700","program":"特别呈现(106)"},{"start":"09:27","startTime":"20260417092700","stopTime":"20260417102600","program":"寰宇视野(90)"},{"start":"10:26","startTime":"20260417102600","stopTime":"20260417112500","program":"全景自然(77)"},{"start":"11:25","startTime":"20260417112500","stopTime":"20260417122700","program":"魅力万象(77)"},{"start":"12:27","startTime":"20260417122700","stopTime":"20260417133100","program":"全景自然(78)"},{"start":"13:31","startTime":"20260417133100","stopTime":"20260417143000","program":"全景自然(92)"},{"start":"14:30","startTime":"20260417143000","stopTime":"20260417153000","program":"魅力万象(92)"},{"start":"15:30","startTime":"20260417153000","stopTime":"20260417162900","program":"全景自然(93)"},{"start":"16:29","startTime":"20260417162900","stopTime":"20260417172800","program":"魅力万象(93)"},{"start":"17:28","startTime":"20260417172800","stopTime":"20260417182700","program":"全景自然(107)"},{"start":"18:27","startTime":"20260417182700","stopTime":"20260417192700","program":"魅力万象(107)"},{"start":"19:27","startTime":"20260417192700","stopTime":"20260417200000","program":"活力·源(107)"},{"start":"20:00","startTime":"20260417200000","stopTime":"20260417210000","program":"特别呈现(107)"},{"start":"21:00","startTime":"20260417210000","stopTime":"20260417220400","program":"寰宇视野(107)"},{"start":"22:04","startTime":"20260417220400","stopTime":"20260417230600","program":"故事中国(99)"},{"start":"23:06","startTime":"20260417230600","stopTime":"20260417232700","program":"9视频(107)"},{"start":"23:27","startTime":"20260417232700","stopTime":"20260417235959","program":"寰宇视野(107)"},{"start":"00:00","startTime":"20260418000000","stopTime":"20260418003100","program":"寰宇视野(107)"},{"start":"00:31","startTime":"20260418003100","stopTime":"20260418012700","program":"全景自然(107)"},{"start":"01:27","startTime":"20260418012700","stopTime":"20260418022300","program":"魅力万象(107)"},{"start":"02:23","startTime":"20260418022300","stopTime":"20260418025300","program":"活力·源(107)"},{"start":"02:53","startTime":"20260418025300","stopTime":"20260418035400","program":"特别呈现(107)"},{"start":"03:54","startTime":"20260418035400","stopTime":"20260418041100","program":"9视频(107)"},{"start":"04:11","startTime":"20260418041100","stopTime":"20260418044600","program":"活力·源(107)"},{"start":"04:46","startTime":"20260418044600","stopTime":"20260418054200","program":"故事中国(99)"},{"start":"05:42","startTime":"20260418054200","stopTime":"20260418054600","program":"中华人民共和国国歌"},{"start":"05:46","startTime":"20260418054600","stopTime":"20260418064700","program":"全景自然(107)"},{"start":"06:47","startTime":"20260418064700","stopTime":"20260418074300","program":"魅力万象(107)"},{"start":"07:43","startTime":"20260418074300","stopTime":"20260418075900","program":"9视频(107)"},{"start":"07:59","startTime":"20260418075900","stopTime":"20260418093300","program":"纪录影院(14)"},{"start":"09:33","startTime":"20260418093300","stopTime":"20260418103200","program":"寰宇视野(28)"},{"start":"10:32","startTime":"20260418103200","stopTime":"20260418113100","program":"寰宇视野(29)"},{"start":"11:31","startTime":"20260418113100","stopTime":"20260418123200","program":"寰宇视野(79)"},{"start":"12:32","startTime":"20260418123200","stopTime":"20260418133100","program":"寰宇视野(80)"},{"start":"13:31","startTime":"20260418133100","stopTime":"20260418143000","program":"寰宇视野(81)"}]